mbonig_state_machine/__init__.py
mbonig_state_machine/py.typed
mbonig_state_machine/_jsii/__init__.py
mbonig_state_machine/_jsii/state-machine@0.0.37.jsii.tgz
mbonig_state_machine-0.0.37.dist-info/LICENSE
mbonig_state_machine-0.0.37.dist-info/METADATA
mbonig_state_machine-0.0.37.dist-info/WHEEL
mbonig_state_machine-0.0.37.dist-info/top_level.txt
mbonig_state_machine-0.0.37.dist-info/RECORD
