Metadata-Version: 2.1
Name: mbonig.state-machine
Version: 0.0.37
Summary: A Step Function state machine construct focused on working well with the Workflow Studio
Home-page: https://github.com/mbonig/state-machine.git
Author: Matthew Bonig<matthew.bonig@gmail.com>
License: MIT
Project-URL: Source, https://github.com/mbonig/state-machine.git
Classifier: Intended Audience :: Developers
Classifier: Operating System :: OS Independent
Classifier: Programming Language :: JavaScript
Classifier: Programming Language :: Python :: 3 :: Only
Classifier: Programming Language :: Python :: 3.9
Classifier: Programming Language :: Python :: 3.10
Classifier: Programming Language :: Python :: 3.11
Classifier: Typing :: Typed
Classifier: Development Status :: 5 - Production/Stable
Classifier: License :: OSI Approved
Requires-Python: ~=3.9
License-File: LICENSE
Requires-Dist: aws-cdk-lib <3.0.0,>=2.200.0
Requires-Dist: constructs <11.0.0,>=10.3.0
Requires-Dist: jsii <2.0.0,>=1.116.0
Requires-Dist: projen <0.99.0,>=0.98.3
Requires-Dist: publication >=0.0.3
Requires-Dist: typeguard <4.3.0,>=2.13.3
